TFFactory/DataLoader.py
TFFactory/Factory.py
TFFactory/GraphBuilder.py
TFFactory/SupportedFunctions.py
TFFactory/TFFactory.py
TFFactory/TFFactoryException.py
TFFactory/__init__.py
TFFactory-0.1.5002.dist-info/METADATA
TFFactory-0.1.5002.dist-info/RECORD
TFFactory-0.1.5002.dist-info/WHEEL
TFFactory-0.1.5002.dist-info/top_level.txt
