Metadata-Version: 2.1
Name: TFFactory
Version: 0.1.5002
Summary: A mock tensorflow package that constructs JSON objects instead of tensors.
Home-page: https://github.com/Kevdog25/TFFactory
Author: Kevin Welsh
Author-email: kevinwelsh132@gmail.com
License: UNKNOWN
Platform: UNKNOWN
Classifier: Programming Language :: Python :: 3
Classifier: License :: OSI Approved :: MIT License
Classifier: Operating System :: OS Independent
